{
  "cohort": {
    "name": "Spring 2026 — Brownsville",
    "students": 3,
    "certified": 1,
    "avg_weighted_score": 3.03
  },
  "competencies": [
    { "id": 1,  "name": "AI Literacy & Prompting",               "cluster": "AI & Digital Fluency",             "cluster_index": 0, "weight": 0.045  },
    { "id": 2,  "name": "Automation & Workflow Design",           "cluster": "AI & Digital Fluency",             "cluster_index": 0, "weight": 0.045  },
    { "id": 3,  "name": "Digital Research & Synthesis",           "cluster": "AI & Digital Fluency",             "cluster_index": 0, "weight": 0.045  },
    { "id": 4,  "name": "Data Interpretation & Storytelling",     "cluster": "AI & Digital Fluency",             "cluster_index": 0, "weight": 0.045  },
    { "id": 5,  "name": "Problem Framing & Root Cause Analysis",  "cluster": "Product & Entrepreneurial Thinking","cluster_index": 1, "weight": 0.0467 },
    { "id": 6,  "name": "Market & User Research",                 "cluster": "Product & Entrepreneurial Thinking","cluster_index": 1, "weight": 0.0467 },
    { "id": 7,  "name": "Product Ideation & MVP Design",          "cluster": "Product & Entrepreneurial Thinking","cluster_index": 1, "weight": 0.0467 },
    { "id": 8,  "name": "Business Model Thinking",                "cluster": "Product & Entrepreneurial Thinking","cluster_index": 1, "weight": 0.0467 },
    { "id": 9,  "name": "Execution & Iteration",                  "cluster": "Product & Entrepreneurial Thinking","cluster_index": 1, "weight": 0.0467 },
    { "id": 10, "name": "Systems Thinking",                       "cluster": "Product & Entrepreneurial Thinking","cluster_index": 1, "weight": 0.0467 },
    { "id": 11, "name": "Self-Awareness & Emotional Regulation",  "cluster": "Leadership & Social Influence",    "cluster_index": 2, "weight": 0.045  },
    { "id": 12, "name": "Team Collaboration & Trust-Building",    "cluster": "Leadership & Social Influence",    "cluster_index": 2, "weight": 0.045  },
    { "id": 13, "name": "Conflict Navigation & Resolution",       "cluster": "Leadership & Social Influence",    "cluster_index": 2, "weight": 0.045  },
    { "id": 14, "name": "Public Speaking & Presentation",         "cluster": "Leadership & Social Influence",    "cluster_index": 2, "weight": 0.045  },
    { "id": 15, "name": "Coaching & Mentoring Others",            "cluster": "Leadership & Social Influence",    "cluster_index": 2, "weight": 0.045  },
    { "id": 16, "name": "Negotiation & Persuasion",               "cluster": "Leadership & Social Influence",    "cluster_index": 2, "weight": 0.045  },
    { "id": 17, "name": "Resume & LinkedIn Presence",             "cluster": "Professional Readiness",           "cluster_index": 3, "weight": 0.0425 },
    { "id": 18, "name": "Interview Readiness",                    "cluster": "Professional Readiness",           "cluster_index": 3, "weight": 0.0425 },
    { "id": 19, "name": "Professional Communication",             "cluster": "Professional Readiness",           "cluster_index": 3, "weight": 0.0425 },
    { "id": 20, "name": "Networking & Relationship Building",     "cluster": "Professional Readiness",           "cluster_index": 3, "weight": 0.0425 },
    { "id": 21, "name": "Cultural Competence & Inclusion",        "cluster": "Community & Social Impact",        "cluster_index": 4, "weight": 0.05   },
    { "id": 22, "name": "Community Problem-Solving",              "cluster": "Community & Social Impact",        "cluster_index": 4, "weight": 0.05   }
  ],
  "students": [
    {
      "id": "student_1",
      "name": "Maria Garcia",
      "team": "Team A",
      "scores": {
        "self_scores":  [4, 4, 4, 3,  4, 3, 4, 4, 4, 3,  4, 4, 3, 4, 4, 4,  4, 4, 4, 3,  4, 4],
        "peer_avg":     [3.8, 3.7, 3.9, 3.5,  3.8, 3.2, 3.9, 3.7, 3.9, 3.1,  3.9, 3.8, 3.2, 3.9, 3.5, 2.3,  3.6, 3.9, 3.8, 3.2,  3.8, 3.6],
        "peer_count":   [3, 3, 4, 3,  3, 3, 4, 3, 3, 3,  3, 3, 3, 4, 3, 3,  3, 4, 3, 3,  3, 3],
        "staff_avg":    [4.0, 3.5, 4.0, 3.5,  4.0, 3.5, 4.0, 3.5, 4.0, 3.5,  4.0, 3.5, 3.5, 4.0, 3.5, 3.5,  4.0, 3.5, 4.0, 3.5,  4.0, 3.5],
        "staff_count":  [2, 2, 2, 2,  2, 2, 2, 2, 2, 2,  2, 2, 2, 2, 2, 2,  2, 2, 2, 2,  2, 2]
      },
      "cluster_averages": {
        "ai_digital":   3.7,
        "product":      3.6,
        "leadership":   3.4,
        "professional": 3.6,
        "community":    3.7
      },
      "weighted_overall": 3.57,
      "certification": {
        "status":           "CERTIFIED",
        "meets_score_bar":  true,
        "sprints_complete": true,
        "demo_day":         true,
        "negotiation_sim":  true
      },
      "flags": {
        "perception_gaps": [
          {
            "competency_id":   16,
            "competency_name": "Negotiation & Persuasion",
            "self_score":      4.0,
            "peer_avg":        2.3,
            "gap":             1.7
          }
        ],
        "staff_divergence": []
      }
    },
    {
      "id": "student_2",
      "name": "Diego Reyes",
      "team": "Team B",
      "scores": {
        "self_scores":  [3, 3, 4, 3,  3, 3, 3, 4, 3, 3,  4, 3, 3, 4, 3, 3,  3, 4, 3, 3,  3, 3],
        "peer_avg":     [3.2, 3.0, 3.5, 3.1,  3.3, 3.0, 3.2, 3.5, 3.2, 2.9,  3.6, 3.1, 3.0, 3.5, 3.2, 3.0,  3.1, 3.4, 3.2, 2.9,  3.2, 3.0],
        "peer_count":   [3, 3, 3, 3,  3, 3, 4, 3, 3, 3,  3, 3, 3, 3, 3, 3,  3, 3, 3, 3,  3, 3],
        "staff_avg":    [3.5, 3.0, 3.5, 3.0,  3.5, 3.0, 3.5, 3.5, 3.0, 3.0,  3.5, 3.0, 3.0, 3.5, 3.0, 3.0,  3.0, 3.5, 3.0, 3.0,  3.5, 3.0],
        "staff_count":  [2, 2, 2, 2,  2, 2, 2, 2, 2, 2,  2, 2, 2, 2, 2, 2,  2, 2, 2, 2,  2, 2]
      },
      "cluster_averages": {
        "ai_digital":   3.2,
        "product":      3.2,
        "leadership":   3.2,
        "professional": 3.2,
        "community":    3.1
      },
      "weighted_overall": 3.19,
      "certification": {
        "status":           "CONDITIONAL",
        "meets_score_bar":  true,
        "sprints_complete": true,
        "demo_day":         false,
        "negotiation_sim":  true
      },
      "flags": {
        "perception_gaps":  [],
        "staff_divergence": []
      }
    },
    {
      "id": "student_3",
      "name": "Ana Flores",
      "team": "Team B",
      "scores": {
        "self_scores":  [3, 2, 3, 2,  3, 2, 2, 3, 2, 2,  3, 2, 2, 3, 2, 2,  3, 2, 3, 2,  3, 2],
        "peer_avg":     [2.3, 2.0, 2.5, 2.1,  2.7, 2.0, 2.3, 2.5, 2.1, 2.2,  2.8, 2.3, 2.1, 2.5, 2.2, 2.0,  2.7, 2.4, 2.8, 2.1,  2.5, 2.3],
        "peer_count":   [3, 3, 3, 3,  3, 3, 3, 3, 3, 3,  3, 3, 3, 3, 3, 3,  3, 3, 3, 3,  3, 3],
        "staff_avg":    [2.5, 2.0, 2.5, 2.0,  2.5, 2.0, 2.5, 2.5, 2.0, 2.0,  3.0, 2.5, 2.0, 2.5, 2.0, 2.0,  2.5, 2.0, 2.5, 2.0,  2.5, 2.0],
        "staff_count":  [2, 2, 2, 2,  2, 2, 2, 2, 2, 2,  2, 2, 2, 2, 2, 2,  2, 2, 2, 2,  2, 2]
      },
      "cluster_averages": {
        "ai_digital":   2.2,
        "product":      2.3,
        "leadership":   2.3,
        "professional": 2.5,
        "community":    2.4
      },
      "weighted_overall": 2.33,
      "certification": {
        "status":           "NOT_CERTIFIED",
        "meets_score_bar":  false,
        "sprints_complete": false,
        "demo_day":         false,
        "negotiation_sim":  false
      },
      "flags": {
        "perception_gaps":  [],
        "staff_divergence": []
      }
    }
  ],
  "cohort_analytics": {
    "strongest_competencies": [
      "Public Speaking & Presentation",
      "AI Literacy & Prompting",
      "Team Collaboration & Trust-Building"
    ],
    "weakest_competencies": [
      "Automation & Workflow Design",
      "Negotiation & Persuasion",
      "Community Problem-Solving"
    ],
    "avg_self_vs_peer_gap": 0.31,
    "cluster_rankings": [
      { "cluster": "Professional Readiness",           "avg_score": 3.10, "rank": 1 },
      { "cluster": "Community & Social Impact",        "avg_score": 3.07, "rank": 2 },
      { "cluster": "AI & Digital Fluency",             "avg_score": 3.03, "rank": 3 },
      { "cluster": "Product & Entrepreneurial Thinking","avg_score": 3.03, "rank": 4 },
      { "cluster": "Leadership & Social Influence",    "avg_score": 2.97, "rank": 5 }
    ]
  }
}
